PyBMICalculator/__init__.py
PyBMICalculator/bmi_calculator.py
PyBMICalculator-0.1.0.dist-info/License
PyBMICalculator-0.1.0.dist-info/METADATA
PyBMICalculator-0.1.0.dist-info/WHEEL
PyBMICalculator-0.1.0.dist-info/top_level.txt
PyBMICalculator-0.1.0.dist-info/RECORD
