Metadata-Version: 2.1
Name: PyBMICalculator
Version: 0.1.0
Summary: A simple BMI Calculator that calculates and categorizes BMI based on weight and height.
Author: Md. Ismiel Hossen Abir
Author-email: ismielabir1971@gmail.com
Classifier: Programming Language :: Python :: 3
Classifier: License :: OSI Approved :: MIT License
Classifier: Operating System :: OS Independent
License-File: License
